absurdia/__init__.py
absurdia/absurdia_object.py
absurdia/agent_credentials.py
absurdia/api_error.py
absurdia/api_response.py
absurdia/util.py
absurdia/version.py
absurdia/cli/__init__.py
absurdia/cli/common.py
absurdia/cli/importers/__init__.py
absurdia/cli/importers/freqtrade.py
absurdia/clients/__init__.py
absurdia/clients/http_client.py
absurdia/resources/__init__.py
absurdia/resources/accounts.py
absurdia/resources/agents.py
absurdia/resources/backtests.py
absurdia/resources/strategies.py
absurdia/resources/users.py
absurdia-0.0.6.dist-info/LICENSE
absurdia-0.0.6.dist-info/METADATA
absurdia-0.0.6.dist-info/WHEEL
absurdia-0.0.6.dist-info/entry_points.txt
absurdia-0.0.6.dist-info/top_level.txt
absurdia-0.0.6.dist-info/zip-safe
absurdia-0.0.6.dist-info/RECORD
