Metadata-Version: 2.1
Name: absurdia
Version: 0.0.6
Summary: Python bindings for the Absurdia API
Home-page: https://github.com/absurdia/absurdia-py
Author: Absurdia
Author-email: support@absurdia.markets
License: MIT
Project-URL: Bug Tracker, https://github.com/absurdia/absurdia-py/issues
Project-URL: Changes, https://github.com/absurdia/absurdia-py/blob/master/CHANGELOG.md
Project-URL: Source Code, https://github.com/absurdia/absurdia-py
Keywords: absurdia api trading
Classifier: Development Status :: 3 - Alpha
Classifier: Intended Audience :: Developers
Classifier: License :: OSI Approved :: MIT License
Classifier: Operating System :: OS Independent
Classifier: Programming Language :: Python
Classifier: Programming Language :: Python :: 3
Classifier: Programming Language :: Python :: 3.4
Classifier: Programming Language :: Python :: 3.5
Classifier: Programming Language :: Python :: 3.6
Classifier: Programming Language :: Python :: 3.7
Classifier: Programming Language :: Python :: 3.8
Classifier: Programming Language :: Python :: 3.9
Classifier: Programming Language :: Python :: 3.10
Classifier: Programming Language :: Python :: 3.11
Classifier: Programming Language :: Python :: Implementation :: PyPy
Classifier: Topic :: Software Development :: Libraries :: Python Modules
Requires-Python: >=3.4, !=3.0.*, !=3.1.*, !=3.2.*, !=3.3.*
License-File: LICENSE
Requires-Dist: click
Requires-Dist: brotlipy
Requires-Dist: psutil
Requires-Dist: colorama
Requires-Dist: requests
